youtubetobibtex/__init__.py
youtubetobibtex/cli.py
youtubetobibtex/client.py
youtubetobibtex/errors.py
youtubetobibtex-0.1.3.dist-info/LICENSE
youtubetobibtex-0.1.3.dist-info/METADATA
youtubetobibtex-0.1.3.dist-info/WHEEL
youtubetobibtex-0.1.3.dist-info/entry_points.txt
youtubetobibtex-0.1.3.dist-info/top_level.txt
youtubetobibtex-0.1.3.dist-info/RECORD
