Metadata-Version: 2.1
Name: youtubetobibtex
Version: 0.1.3
Summary: Get bibtex entry for a video from its url
Home-page: https://github.com/nanoy42/youtubetobibtex
Author: Yoann Piétri
License: GPLv3
Keywords: youtube,bibtex
Platform: UNKNOWN
Classifier: Development Status :: 4 - Beta
Classifier: Programming Language :: Python :: 3
Classifier: License :: OSI Approved :: GNU General Public License v3 (GPLv3)
Classifier: Operating System :: OS Independent
Classifier: Natural Language :: English
Classifier: Topic :: Multimedia :: Video
License-File: LICENSE
Requires-Dist: google-api-python-client
